LICENSE
README.md
graphql_jwt/__init__.py
graphql_jwt/backends.py
graphql_jwt/compat.py
graphql_jwt/decorators.py
graphql_jwt/exceptions.py
graphql_jwt/locale/ar/LC_MESSAGES/django.mo
graphql_jwt/locale/ar/LC_MESSAGES/django.po
graphql_jwt/locale/es/LC_MESSAGES/django.mo
graphql_jwt/locale/es/LC_MESSAGES/django.po
graphql_jwt/locale/fr/LC_MESSAGES/django.mo
graphql_jwt/locale/fr/LC_MESSAGES/django.po
graphql_jwt/locale/nl/LC_MESSAGES/django.mo
graphql_jwt/locale/nl/LC_MESSAGES/django.po
graphql_jwt/locale/pt_BR/LC_MESSAGES/django.mo
graphql_jwt/locale/pt_BR/LC_MESSAGES/django.po
graphql_jwt/locale/zh_Hans/LC_MESSAGES/django.po
graphql_jwt/middleware.py
graphql_jwt/mixins.py
graphql_jwt/mutations.py
graphql_jwt/path.py
graphql_jwt/refresh_token/__init__.py
graphql_jwt/refresh_token/admin/__init__.py
graphql_jwt/refresh_token/admin/filters.py
graphql_jwt/refresh_token/apps.py
graphql_jwt/refresh_token/decorators.py
graphql_jwt/refresh_token/locale/ar/LC_MESSAGES/django.mo
graphql_jwt/refresh_token/locale/ar/LC_MESSAGES/django.po
graphql_jwt/refresh_token/locale/es/LC_MESSAGES/django.mo
graphql_jwt/refresh_token/locale/es/LC_MESSAGES/django.po
graphql_jwt/refresh_token/locale/fr/LC_MESSAGES/django.mo
graphql_jwt/refresh_token/locale/fr/LC_MESSAGES/django.po
graphql_jwt/refresh_token/locale/nl/LC_MESSAGES/django.mo
graphql_jwt/refresh_token/locale/nl/LC_MESSAGES/django.po
graphql_jwt/refresh_token/locale/pt_BR/LC_MESSAGES/django.mo
graphql_jwt/refresh_token/locale/pt_BR/LC_MESSAGES/django.po
graphql_jwt/refresh_token/locale/zh_Hans/LC_MESSAGES/django.po
graphql_jwt/refresh_token/management/__init__.py
graphql_jwt/refresh_token/management/commands/__init__.py
graphql_jwt/refresh_token/management/commands/cleartokens.py
graphql_jwt/refresh_token/managers.py
graphql_jwt/refresh_token/migrations/0001_initial.py
graphql_jwt/refresh_token/migrations/0002_auto_20190130_0900.py
graphql_jwt/refresh_token/migrations/__init__.py
graphql_jwt/refresh_token/mixins.py
django_graphql_jwt_patch-0.3.4.0.dist-info/LICENSE
django_graphql_jwt_patch-0.3.4.0.dist-info/WHEEL
django_graphql_jwt_patch-0.3.4.0.dist-info/METADATA
django_graphql_jwt_patch-0.3.4.0.dist-info/RECORD
