Metadata-Version: 2.1
Name: django-graphql-jwt-patch
Version: 0.3.4.0
Summary: JSON Web Token for Django GraphQL.
Home-page: https://github.com/gabrielsebag/django-graphql-jwt
License: MIT
Keywords: django,graphql,jwt
Author: Gabriel Sebag
Author-email: hello@gabrielsebag.com
Requires-Python: >=3.6,<4.0
Classifier: Development Status :: 4 - Beta
Classifier: Environment :: Web Environment
Classifier: Framework :: Django
Classifier: Framework :: Django :: 2.0
Classifier: Framework :: Django :: 2.1
Classifier: Framework :: Django :: 2.2
Classifier: Framework :: Django :: 3.0
Classifier: Framework :: Django :: 3.1
Classifier: Framework :: Django :: 3.2
Classifier: Intended Audience :: Developers
Classifier: Intended Audience :: Information Technology
Classifier: Intended Audience :: System Administrators
Classifier: License :: OSI Approved :: MIT License
Classifier: Operating System :: OS Independent
Classifier: Programming Language :: Python
Classifier: Programming Language :: Python :: 3
Classifier: Programming Language :: Python :: 3.6
Classifier: Programming Language :: Python :: 3.7
Classifier: Programming Language :: Python :: 3.8
Classifier: Programming Language :: Python :: 3.9
Classifier: Programming Language :: Python :: 3.10
Classifier: Programming Language :: Python :: 3.11
Classifier: Programming Language :: Python :: 3
Classifier: Programming Language :: Python :: 3.6
Classifier: Programming Language :: Python :: 3.7
Classifier: Programming Language :: Python :: 3.8
Classifier: Programming Language :: Python :: 3.9
Classifier: Topic :: Internet
Classifier: Topic :: Internet :: WWW/HTTP
Classifier: Topic :: Internet :: WWW/HTTP :: HTTP Servers
Classifier: Topic :: Security
Classifier: Topic :: Software Development
Classifier: Topic :: Software Development :: Libraries
Classifier: Topic :: Software Development :: Libraries :: Python Modules
Requires-Dist: Django (>=2.0)
Requires-Dist: PyJWT (>=2,<3)
Requires-Dist: graphene (>=2.1.5)
Requires-Dist: graphene-django-patch (>=2.0.0)
Project-URL: Documentation, https://django-graphql-jwt.domake.io
Project-URL: Repository, https://github.com/gabrielsebag/django-graphql-jwt
